edinet_explorer/__about__.py
edinet_explorer/__init__.py
edinet_explorer/__main__.py
edinet_explorer/data_processor.py
edinet_explorer/explorer_gui.py
edinet_explorer/resources/icons/folder.png
edinet_explorer/resources/icons/icon_win.ico
edinet_explorer-0.1.0.dist-info/METADATA
edinet_explorer-0.1.0.dist-info/WHEEL
edinet_explorer-0.1.0.dist-info/entry_points.txt
edinet_explorer-0.1.0.dist-info/licenses/LICENSE
edinet_explorer-0.1.0.dist-info/RECORD
