Metadata-Version: 2.3
Name: edinet-explorer
Version: 0.1.0
Summary: A Python-based GUI application for data collection from EDINET
Project-URL: Source, https://github.com/vincent-lpj/edinet-explorer
Author-email: Peijun Liu <vincentlpj.ou@gmail.com>
License-Expression: MIT
License-File: LICENSE
Keywords: annual reports,edinet,xbrl
Classifier: Development Status :: 4 - Beta
Classifier: Programming Language :: Python
Classifier: Programming Language :: Python :: 3.8
Classifier: Programming Language :: Python :: 3.9
Classifier: Programming Language :: Python :: 3.10
Classifier: Programming Language :: Python :: 3.11
Classifier: Programming Language :: Python :: 3.12
Classifier: Programming Language :: Python :: Implementation :: CPython
Classifier: Programming Language :: Python :: Implementation :: PyPy
Requires-Python: >=3.8
Requires-Dist: ctkmessagebox
Requires-Dist: pandas
Requires-Dist: requests
